graph_editor_jupyter/__init__.py
graph_editor_jupyter/debug.py
graph_editor_jupyter/edit.py
graph_editor_jupyter/fancy_drawing.py
graph_editor_jupyter/graph_physics.py
graph_editor_jupyter/graphics.py
graph_editor_jupyter/settings.py
graph_editor_jupyter/subscribe.py
graph_editor_jupyter/visual_graph.py
graph_editor_jupyter-0.0.7.dist-info/licenses/LICENSE
graph_editor_jupyter-0.0.7.dist-info/METADATA
graph_editor_jupyter-0.0.7.dist-info/WHEEL
graph_editor_jupyter-0.0.7.dist-info/top_level.txt
graph_editor_jupyter-0.0.7.dist-info/RECORD
